eden_simulator-0.2.3.dist-info/METADATA
eden_simulator-0.2.3.dist-info/entry_points.txt
eden_simulator-0.2.3.dist-info/RECORD
eden_simulator-0.2.3.dist-info/WHEEL
eden_simulator-0.2.3.dist-info/top_level.txt
eden_simulator.libs/libgomp-d22c30c5.so.1.0.0
eden_simulator/version.py
eden_simulator/run_sim.py
eden_simulator/embeden.py
eden_simulator/__init__.py
eden_simulator/command_line.py
eden_simulator/data/bin/eden
