Metadata-Version: 2.1
Name: eden-simulator
Version: 0.2.3
Summary: Standalone Python wheels for the EDEN neural simulator
Home-page: https://gitlab.com/neurocomputing-lab/Inferior_OliveEMC/eden
Author: Sotirios Panagotou
Author-email: s.panagiotou@erasmusmc.nl
License: UNKNOWN
Download-URL: https://gitlab.com/neurocomputing-lab/Inferior_OliveEMC/eden/-/archive/main/eden-main.zip
Keywords: simulator,simulation,HPC,neuroscience,NeuroML
Platform: windows
Platform: mac
Platform: linux
Classifier: Intended Audience :: Science/Research
Classifier: Topic :: Scientific/Engineering :: Bio-Informatics
Classifier: Environment :: Console
Classifier: Operating System :: Microsoft :: Windows
Classifier: Operating System :: MacOS
Classifier: Operating System :: POSIX :: Linux
Classifier: License :: OSI Approved :: GNU General Public License v3 (GPLv3)
Classifier: Development Status :: 3 - Alpha
Classifier: Programming Language :: C++
Classifier: Programming Language :: Python :: 3
Requires-Python: >=3.2
Requires-Dist: numpy
Requires-Dist: lxml
